evc/__init__.py
evc/tests/__init__.py
evc/tests/test_intergration_with_eve.py
evc-0.6.1.dist-info/LICENSE
evc-0.6.1.dist-info/METADATA
evc-0.6.1.dist-info/WHEEL
evc-0.6.1.dist-info/top_level.txt
evc-0.6.1.dist-info/RECORD
